bloqade/device.py
bloqade/task.py
bloqade/test_utils.py
bloqade/types.py
bloqade/analysis/__init__.py
bloqade/analysis/address/__init__.py
bloqade/analysis/address/analysis.py
bloqade/analysis/address/impls.py
bloqade/analysis/address/lattice.py
bloqade/analysis/fidelity/__init__.py
bloqade/analysis/fidelity/analysis.py
bloqade/analysis/measure_id/__init__.py
bloqade/analysis/measure_id/analysis.py
bloqade/analysis/measure_id/impls.py
bloqade/analysis/measure_id/lattice.py
bloqade/annotate/__init__.py
bloqade/annotate/_dialect.py
bloqade/annotate/_interface.py
bloqade/annotate/stmts.py
bloqade/annotate/types.py
bloqade/cirq_utils/__init__.py
bloqade/cirq_utils/lineprog.py
bloqade/cirq_utils/lowering.py
bloqade/cirq_utils/parallelize.py
bloqade/cirq_utils/emit/__init__.py
bloqade/cirq_utils/emit/base.py
bloqade/cirq_utils/emit/gate.py
bloqade/cirq_utils/emit/noise.py
bloqade/cirq_utils/emit/qubit.py
bloqade/cirq_utils/noise/__init__.py
bloqade/cirq_utils/noise/_two_zone_utils.py
bloqade/cirq_utils/noise/conflict_graph.py
bloqade/cirq_utils/noise/model.py
bloqade/cirq_utils/noise/transform.py
bloqade/gemini/__init__.py
bloqade/gemini/analysis/__init__.py
bloqade/gemini/analysis/logical_validation/__init__.py
bloqade/gemini/analysis/logical_validation/analysis.py
bloqade/gemini/analysis/logical_validation/impls.py
bloqade/gemini/dialects/__init__.py
bloqade/gemini/dialects/logical/__init__.py
bloqade/gemini/dialects/logical/_dialect.py
bloqade/gemini/dialects/logical/_interface.py
bloqade/gemini/dialects/logical/groups.py
bloqade/gemini/dialects/logical/stmts.py
bloqade/gemini/rewrite/__init__.py
bloqade/gemini/rewrite/initialize.py
bloqade/native/__init__.py
bloqade/native/_prelude.py
bloqade/native/dialects/__init__.py
bloqade/native/dialects/gate/__init__.py
bloqade/native/dialects/gate/_dialect.py
bloqade/native/dialects/gate/_interface.py
bloqade/native/dialects/gate/stmts.py
bloqade/native/stdlib/__init__.py
bloqade/native/stdlib/broadcast.py
bloqade_circuit-0.10.6.dist-info/METADATA
bloqade_circuit-0.10.6.dist-info/WHEEL
bloqade_circuit-0.10.6.dist-info/licenses/LICENSE
bloqade_circuit-0.10.6.dist-info/RECORD
