Metadata-Version: 2.4
Name: bloqade-circuit
Version: 0.10.6
Summary: The software development toolkit for neutral atom arrays.
Author-email: Roger-luo <rluo@quera.com>, kaihsin <khwu@quera.com>, weinbe58 <pweinberg@quera.com>, johnzl-777 <jlong@quera.com>
License-File: LICENSE
Requires-Python: >=3.10
Requires-Dist: kirin-toolchain<0.23.0,>=0.21.0
Requires-Dist: numpy>=1.22.0
Requires-Dist: pandas>=2.2.3
Requires-Dist: pydantic<2.11.0,>=1.3.0
Requires-Dist: pyqrack-cpu>=1.70.4
Requires-Dist: rich>=13.9.4
Requires-Dist: scipy>=1.13.1
Provides-Extra: cirq
Requires-Dist: cirq-core>=1.4.1; extra == 'cirq'
Requires-Dist: cirq-core[contrib]>=1.4.1; extra == 'cirq'
Requires-Dist: numba>=0.63.1; extra == 'cirq'
Requires-Dist: qpsolvers[clarabel]>=4.7.0; extra == 'cirq'
Provides-Extra: pyqrack-cuda
Requires-Dist: pyqrack-cuda>=1.70.4; extra == 'pyqrack-cuda'
Provides-Extra: pyqrack-opencl
Requires-Dist: pyqrack>=1.70.4; extra == 'pyqrack-opencl'
Provides-Extra: qasm2
Requires-Dist: lark>=1.2.2; extra == 'qasm2'
Provides-Extra: qbraid
Requires-Dist: qbraid>=0.9.3; extra == 'qbraid'
Provides-Extra: stim
Requires-Dist: stim>=1.15.0; extra == 'stim'
Provides-Extra: vis
Requires-Dist: ffmpeg>=1.4; extra == 'vis'
Requires-Dist: matplotlib>=3.9.2; extra == 'vis'
Requires-Dist: pyqt5>=5.15.11; (sys_platform == 'darwin') and extra == 'vis'
Requires-Dist: pyqt5>=5.15.11; (sys_platform == 'linux') and extra == 'vis'
Requires-Dist: tqdm>=4.66.5; extra == 'vis'
